tensor_library/TensorLibrary.py
tensor_library/__innit__.py
TensorLibrary-1.0.0.dist-info/LICENSE
TensorLibrary-1.0.0.dist-info/METADATA
TensorLibrary-1.0.0.dist-info/WHEEL
TensorLibrary-1.0.0.dist-info/top_level.txt
TensorLibrary-1.0.0.dist-info/RECORD
