Metadata-Version: 2.1
Name: TensorLibrary
Version: 1.0.0
Summary: A package made to handle and manipulate tensors
Author-email: Gabriel Picard <gab_picard@yahoo.com>
Project-URL: Homepage, https://github.com/gabPicard/Tensor-Library
Classifier: Programming Language :: Python :: 3
Classifier: License :: OSI Approved :: MIT License
Classifier: Operating System :: OS Independent
Requires-Python: >=3.8
License-File: LICENSE
